examples/__init__.py
examples/anthropic_example/__init__.py
examples/anthropic_example/completion.py
examples/autogen_example/__init__.py
examples/autogen_example/main.py
examples/awsbedrock_examples/__init__.py
examples/awsbedrock_examples/converse.py
examples/azureopenai_example/__init__.py
examples/azureopenai_example/completion.py
examples/cerebras_example/__init__.py
examples/cerebras_example/main.py
examples/chroma_example/__init__.py
examples/chroma_example/basic.py
examples/cleanlab_example/simple.py
examples/cohere_example/__init__.py
examples/cohere_example/chat.py
examples/cohere_example/chat_stream.py
examples/cohere_example/chat_streamv2.py
examples/cohere_example/chatv2.py
examples/cohere_example/embed.py
examples/cohere_example/rerank.py
examples/cohere_example/rerankv2.py
examples/cohere_example/tools.py
examples/crewai_example/__init__.py
examples/crewai_example/basic.py
examples/crewai_example/instagram_post/__init__.py
examples/crewai_example/instagram_post/agents.py
examples/crewai_example/instagram_post/main.py
examples/crewai_example/instagram_post/tasks.py
examples/crewai_example/instagram_post/tools/__init__.py
examples/crewai_example/instagram_post/tools/browser_tools.py
examples/crewai_example/simple_agent/__init__.py
examples/crewai_example/simple_agent/agents.py
examples/crewai_example/simple_agent/main.py
examples/crewai_example/simple_agent/tasks.py
examples/crewai_example/trip_planner/__init__.py
examples/crewai_example/trip_planner/agents.py
examples/crewai_example/trip_planner/main.py
examples/crewai_example/trip_planner/tasks.py
examples/crewai_example/trip_planner/tools/calculator.py
examples/crewai_example/trip_planner/tools/search_tools.py
examples/dspy_example/QA_basic.py
examples/dspy_example/QA_basic_with_chain_of_thought.py
examples/dspy_example/QA_basic_with_signature.py
examples/dspy_example/QA_multi_step_with_chain_of_thought.py
examples/dspy_example/math_problems_cot.py
examples/dspy_example/math_problems_cot_parallel.py
langtrace_python_sdk-3.8.18.dist-info/METADATA
langtrace_python_sdk-3.8.18.dist-info/WHEEL
langtrace_python_sdk-3.8.18.dist-info/entry_points.txt
langtrace_python_sdk-3.8.18.dist-info/licenses/LICENSE
langtrace_python_sdk-3.8.18.dist-info/RECORD
