Metadata-Version: 2.4
Name: langtrace-python-sdk
Version: 3.8.18
Summary: Python SDK for LangTrace
Project-URL: Homepage, https://github.com/Scale3-Labs/langtrace-python-sdk
Author-email: Scale3 Labs <engineering@scale3labs.com>
License-Expression: Apache-2.0
License-File: LICENSE
Classifier: License :: OSI Approved :: Apache Software License
Classifier: Operating System :: OS Independent
Classifier: Programming Language :: Python :: 3
Requires-Python: >=3.9
Requires-Dist: boto3==1.38.0
Requires-Dist: colorama>=0.4.6
Requires-Dist: fsspec>=2024.6.0
Requires-Dist: opentelemetry-api>=1.25.0
Requires-Dist: opentelemetry-exporter-otlp-proto-grpc>=1.25.0
Requires-Dist: opentelemetry-exporter-otlp-proto-http>=1.25.0
Requires-Dist: opentelemetry-instrumentation-sqlalchemy>=0.46b0
Requires-Dist: opentelemetry-instrumentation>=0.47b0
Requires-Dist: opentelemetry-sdk>=1.25.0
Requires-Dist: sentry-sdk>=2.14.0
Requires-Dist: setuptools
Requires-Dist: sqlalchemy
Requires-Dist: tiktoken>=0.1.1
Requires-Dist: trace-attributes==7.2.1
Requires-Dist: transformers>=4.11.3
Requires-Dist: ujson>=5.10.0
Provides-Extra: dev
Requires-Dist: anthropic; extra == 'dev'
Requires-Dist: chromadb; extra == 'dev'
Requires-Dist: cohere; extra == 'dev'
Requires-Dist: embedchain; extra == 'dev'
Requires-Dist: google-cloud-aiplatform; extra == 'dev'
Requires-Dist: google-generativeai; extra == 'dev'
Requires-Dist: graphlit-client; extra == 'dev'
Requires-Dist: groq; extra == 'dev'
Requires-Dist: langchain; extra == 'dev'
Requires-Dist: langchain-community; extra == 'dev'
Requires-Dist: langchain-openai; extra == 'dev'
Requires-Dist: litellm==1.48.7; extra == 'dev'
Requires-Dist: mistralai; extra == 'dev'
Requires-Dist: ollama; extra == 'dev'
Requires-Dist: openai-agents>=0.0.3; extra == 'dev'
Requires-Dist: openai>=1.60.0; extra == 'dev'
Requires-Dist: phidata; extra == 'dev'
Requires-Dist: pinecone; extra == 'dev'
Requires-Dist: python-dotenv; extra == 'dev'
Requires-Dist: qdrant-client; extra == 'dev'
Requires-Dist: weaviate-client; extra == 'dev'
Provides-Extra: test
Requires-Dist: pytest; extra == 'test'
Requires-Dist: pytest-asyncio; extra == 'test'
Requires-Dist: pytest-vcr; extra == 'test'
